Workbook
Name DateEval: Hypotheses!$B$6
Name AgeRetraite: Hypotheses!$B$7
Name TauxTech: Hypotheses!$B$8
Name TxSal: Hypotheses!$B$9
Name TxTurnover: Hypotheses!$B$10
Name TxLic: Hypotheses!$B$11
Name FraisIFC: Hypotheses!$B$12
Name FraisIFCP: Hypotheses!$B$13
Name DureeAmort: Hypotheses!$B$14

Sheet Hypotheses
A1: SIMULATEUR IFC / IFC+ — ÉVALUATION ACTUARIELLE DU PASSIF SOCIAL
A3: Entreprise | B3: SENIA S.A. — Sénégalaise des Industries Alimentaires
A4: Localisation | B4: Zone industrielle de Dakar, Sénégal
A5: Convention collective | B5: Convention Collective Nationale Interprofessionnelle (CCNI) du Sénégal
A6: Date d'évaluation | B6: 46022
A7: Âge de départ à la retraite (IPRES) | B7: 60
A8: Taux technique (actualisation) | B8: 0.035
A9: Taux d'évolution des salaires | B9: 0.02
A10: Taux de turn-over | B10: 0.02
A11: Taux annuel de licenciement (par défaut) | B11: 0.01
A12: Frais de gestion IFC | B12: 0.02
A13: Frais de gestion IFC+ | B13: 0.02
A14: Durée d'amortissement de la dette actuarielle (ans) | B14: 5
A15: Taux d'imposition des sociétés (info) | B15: 0.3
A16: SMIG mensuel légal (info, FCFA) | B16: 43440
A17: Table de mortalité | B17: CIMA H (art. 338 du Code CIMA)
A18: Méthode d'évaluation | B18: Méthode prospective (droits projetés au terme, prorata d'ancienneté)

Sheet BD
A1: Matricule | B1: Nom et Prénoms | C1: Catégorie | D1: Sexe | E1: Date de naissance | F1: Date d'embauche | G1: Salaire mensuel brut (FCFA) | H1: Salaire annuel brut (FCFA)
A2: 1 | B2: Mendy Dieynaba | C2: Employé | D2: F | E2: 24438 | F2: 41051 | G2: 168600 | H2: =G2*12
A3: 2 | B3: Thiam Boubacar | C3: Employé | D3: M | E3: 24489 | F3: 35492 | G3: 257100 | H3: =G3*12
A4: 3 | B4: Niang Sokhna | C4: Ouvrier | D4: F | E4: 24672 | F4: 37013 | G4: 121100 | H4: =G4*12
A5: 4 | B5: Kane Saliou | C5: Agent de maîtrise | D5: M | E5: 24743 | F5: 35027 | G5: 390100 | H5: =G5*12
A6: 5 | B6: Ndoye Adja | C6: Cadre dirigeant | D6: F | E6: 24943 | F6: 41420 | G6: 3017000 | H6: =G6*12
A7: 6 | B7: Camara Astou | C7: Employé | D7: F | E7: 25206 | F7: 42212 | G7: 199800 | H7: =G7*12
A8: 7 | B8: Ba Lamine | C8: Agent de maîtrise | D8: M | E8: 25441 | F8: 39542 | G8: 383900 | H8: =G8*12
A9: 8 | B9: Wade Awa | C9: Cadre dirigeant | D9: F | E9: 25936 | F9: 36998 | G9: 2642800 | H9: =G9*12
A10: 9 | B10: Sow Souleymane | C10: Employé | D10: M | E10: 26137 | F10: 43365 | G10: 279300 | H10: =G10*12
A11: 10 | B11: Lô Sokhna | C11: Ouvrier | D11: F | E11: 26790 | F11: 44169 | G11: 99900 | H11: =G11*12
A12: 11 | B12: Diallo Serigne | C12: Employé | D12: M | E12: 27248 | F12: 44744 | G12: 179600 | H12: =G12*12
A13: 12 | B13: Niang Omar | C13: Agent de maîtrise | D13: M | E13: 27365 | F13: 42695 | G13: 384400 | H13: =G13*12
... A51: 50 | B51: Diagne Salimata | C51: Agent de maîtrise | D51: F | E51: 36739 | F51: 44374 | G51: 632400 | H51: =G51*12

Sheet Baremes
A1: Ancienneté (années) | B1: Droit annuel (% du salaire mensuel) | C1: Cumul (%) | E1: Barème CCNI Sénégal : 20 %/an (années 1 à 5), 30 % (6 à 10), 40 % (11 à 15), 50 % (16 à 20), 60 % au-delà.
A2: 0 | B2: =IF(A2=0,0,IF(A2<=5,0.2,IF(A2<=10,0.3,IF(A2<=15,0.4,IF(A2<=20,0.5,0.6))))) | C2: 0
A3: 1 | B3: =IF(A3=0,0,IF(A3<=5,0.2,IF(A3<=10,0.3,IF(A3<=15,0.4,IF(A3<=20,0.5,0.6))))) | C3: =C2+B3
A4: 2 | B4: =IF(A4=0,0,IF(A4<=5,0.2,IF(A4<=10,0.3,IF(A4<=15,0.4,IF(A4<=20,0.5,0.6))))) | C4: =C3+B4
A5: 3 | B5: =IF(A5=0,0,IF(A5<=5,0.2,IF(A5<=10,0.3,IF(A5<=15,0.4,IF(A5<=20,0.5,0.6))))) | C5: =C4+B5
A6: 4 | B6: =IF(A6=0,0,IF(A6<=5,0.2,IF(A6<=10,0.3,IF(A6<=15,0.4,IF(A6<=20,0.5,0.6))))) | C6: =C5+B6
A7: 5 | B7: =IF(A7=0,0,IF(A7<=5,0.2,IF(A7<=10,0.3,IF(A7<=15,0.4,IF(A7<=20,0.5,0.6))))) | C7: =C6+B7
A8: 6 | B8: =IF(A8=0,0,IF(A8<=5,0.2,IF(A8<=10,0.3,IF(A8<=15,0.4,IF(A8<=20,0.5,0.6))))) | C8: =C7+B8
A9: 7 | B9: =IF(A9=0,0,IF(A9<=5,0.2,IF(A9<=10,0.3,IF(A9<=15,0.4,IF(A9<=20,0.5,0.6))))) | C9: =C8+B9
A10: 8 | B10: =IF(A10=0,0,IF(A10<=5,0.2,IF(A10<=10,0.3,IF(A10<=15,0.4,IF(A10<=20,0.5,0.6))))) | C10: =C9+B10
A11: 9 | B11: =IF(A11=0,0,IF(A11<=5,0.2,IF(A11<=10,0.3,IF(A11<=15,0.4,IF(A11<=20,0.5,0.6))))) | C11: =C10+B11
A12: 10 | B12: =IF(A12=0,0,IF(A12<=5,0.2,IF(A12<=10,0.3,IF(A12<=15,0.4,IF(A12<=20,0.5,0.6))))) | C12: =C11+B12
A13: 11 | B13: =IF(A13=0,0,IF(A13<=5,0.2,IF(A13<=10,0.3,IF(A13<=15,0.4,IF(A13<=20,0.5,0.6))))) | C13: =C12+B13
A14: 12 | B14: =IF(A14=0,0,IF(A14<=5,0.2,IF(A14<=10,0.3,IF(A14<=15,0.4,IF(A14<=20,0.5,0.6))))) | C14: =C13+B14
... A62: 60 | B62: =IF(A62=0,0,IF(A62<=5,0.2,IF(A62<=10,0.3,IF(A62<=15,0.4,IF(A62<=20,0.5,0.6))))) | C62: =C61+B62

Sheet Table_CIMA_H
A1: Age x | B1: Lx | C1: dx | D1: qx | E1: Dx | F1: Nx | G1: Cx | H1: Mx
A2: 0 | B2: 1000000 | C2: =B2-B3 | D2: =IF(B2>0,C2/B2,"") | E2: =B2/(1+TauxTech)^A2 | F2: =SUM(E2:$E$108) | G2: =C2/(1+TauxTech)^(A2+0.5) | H2: =SUM(G2:$G$108)
A3: 1 | B3: 994632 | C3: =B3-B4 | D3: =IF(B3>0,C3/B3,"") | E3: =B3/(1+TauxTech)^A3 | F3: =SUM(E3:$E$108) | G3: =C3/(1+TauxTech)^(A3+0.5) | H3: =SUM(G3:$G$108)
A4: 2 | B4: 993906 | C4: =B4-B5 | D4: =IF(B4>0,C4/B4,"") | E4: =B4/(1+TauxTech)^A4 | F4: =SUM(E4:$E$108) | G4: =C4/(1+TauxTech)^(A4+0.5) | H4: =SUM(G4:$G$108)
A5: 3 | B5: 993351 | C5: =B5-B6 | D5: =IF(B5>0,C5/B5,"") | E5: =B5/(1+TauxTech)^A5 | F5: =SUM(E5:$E$108) | G5: =C5/(1+TauxTech)^(A5+0.5) | H5: =SUM(G5:$G$108)
A6: 4 | B6: 992878 | C6: =B6-B7 | D6: =IF(B6>0,C6/B6,"") | E6: =B6/(1+TauxTech)^A6 | F6: =SUM(E6:$E$108) | G6: =C6/(1+TauxTech)^(A6+0.5) | H6: =SUM(G6:$G$108)
A7: 5 | B7: 992474 | C7: =B7-B8 | D7: =IF(B7>0,C7/B7,"") | E7: =B7/(1+TauxTech)^A7 | F7: =SUM(E7:$E$108) | G7: =C7/(1+TauxTech)^(A7+0.5) | H7: =SUM(G7:$G$108)
A8: 6 | B8: 992105 | C8: =B8-B9 | D8: =IF(B8>0,C8/B8,"") | E8: =B8/(1+TauxTech)^A8 | F8: =SUM(E8:$E$108) | G8: =C8/(1+TauxTech)^(A8+0.5) | H8: =SUM(G8:$G$108)
A9: 7 | B9: 991773 | C9: =B9-B10 | D9: =IF(B9>0,C9/B9,"") | E9: =B9/(1+TauxTech)^A9 | F9: =SUM(E9:$E$108) | G9: =C9/(1+TauxTech)^(A9+0.5) | H9: =SUM(G9:$G$108)
A10: 8 | B10: 991460 | C10: =B10-B11 | D10: =IF(B10>0,C10/B10,"") | E10: =B10/(1+TauxTech)^A10 | F10: =SUM(E10:$E$108) | G10: =C10/(1+TauxTech)^(A10+0.5) | H10: =SUM(G10:$G$108)
A11: 9 | B11: 991147 | C11: =B11-B12 | D11: =IF(B11>0,C11/B11,"") | E11: =B11/(1+TauxTech)^A11 | F11: =SUM(E11:$E$108) | G11: =C11/(1+TauxTech)^(A11+0.5) | H11: =SUM(G11:$G$108)
A12: 10 | B12: 990853 | C12: =B12-B13 | D12: =IF(B12>0,C12/B12,"") | E12: =B12/(1+TauxTech)^A12 | F12: =SUM(E12:$E$108) | G12: =C12/(1+TauxTech)^(A12+0.5) | H12: =SUM(G12:$G$108)
A13: 11 | B13: 990541 | C13: =B13-B14 | D13: =IF(B13>0,C13/B13,"") | E13: =B13/(1+TauxTech)^A13 | F13: =SUM(E13:$E$108) | G13: =C13/(1+TauxTech)^(A13+0.5) | H13: =SUM(G13:$G$108)
... A107: 105 | B107: 2 | C107: =B107-B108 | D107: =IF(B107>0,C107/B107,"") | E107: =B107/(1+TauxTech)^A107 | F107: =SUM(E107:$E$108) | G107: =C107/(1+TauxTech)^(A107+0.5) | H107: =SUM(G107:$G$108)
A108: 106 | B108: 0 | C108: =B108 | D108: =IF(B108>0,C108/B108,"") | E108: =B108/(1+TauxTech)^A108 | F108: =SUM(E108:$E$108) | G108: =C108/(1+TauxTech)^(A108+0.5) | H108: =SUM(G108:$G$108)

Sheet Calculs
A1: Matricule | B1: Date de naissance | C1: Date d'embauche | D1: Salaire annuel brut | E1: (1) Ancienneté à la date d'évaluation | F1: (2) Âge exact | G1: Âge (entier) | H1: Date de départ à la retraite | I1: Durée résiduelle n (années) | J1: (3) Salaire final mensuel | K1: (4) Ancienneté au terme | L1: (5) Droits IFC | M1: (6) Probabilité vie | N1: (7) Probabilité présence | O1: (9) Coefficient d'actualisation | P1: (10) VP des prestations futures | Q1: (11) Dette actuarielle | R1: (12) Charge normale | S1: (13) Indemnité de licenciement | T1: (14) Passif IL | U1: (15) Demi-salaire mensuel (IF) | V1: (16) Indemnité IF | W1: (17) Capital décès total (IFC+) | X1: qx (âge actuel) | Y1: Prime pure IFC+
A2: =BD!A2 | B2: =BD!E2 | C2: =BD!F2 | D2: =BD!H2 | E2: =(DateEval-C2)/365.25 | F2: =(DateEval-B2)/365.25 | G2: =TRUNC(F2) | H2: =EDATE(B2,12*AgeRetraite) | I2: =MAX((H2-DateEval)/365.25,0) | J2: =D2/12*(1+TxSal)^MAX(AgeRetraite-G2,0) | K2: =E2+I2 | L2: =(VLOOKUP(TRUNC(K2),Baremes!$A:$C,3,TRUE)+(K2-TRUNC(K2))*VLOOKUP(TRUNC(K2)+1,Baremes!$A:$B,2,TRUE))*J2 | M2: =IF(G2<AgeRetraite,VLOOKUP(AgeRetraite,Table_CIMA_H!$A:$B,2,TRUE)/VLOOKUP(G2,Table_CIMA_H!$A:$B,2,TRUE),1) | N2: =1 | O2: =1/(1+TauxTech)^(I2+0.5) | P2: =L2*M2*N2*O2 | Q2: =P2*E2/K2 | R2: =P2/K2 | S2: =IF(I2<=0,0,VLOOKUP(TRUNC(E2),Baremes!$A:$C,3,TRUE)*D2/12) | T2: =IF(I2<=0,0,S2*TxLic*(1-((1-TxTurnover)/(1+TauxTech))^I2)/(1-(1-TxTurnover)/(1+TauxTech))) | U2: =D2/24 | V2: =IF(I2<=0,0,VLOOKUP(TRUNC(E2),Baremes!$A:$C,3,TRUE)*U2) | W2: =S2+V2 | X2: =(VLOOKUP(G2,Table_CIMA_H!$A:$B,2,TRUE)-VLOOKUP(G2+1,Table_CIMA_H!$A:$B,2,TRUE))/VLOOKUP(G2,Table_CIMA_H!$A:$B,2,TRUE) | Y2: =W2*X2
A3: =BD!A3 | B3: =BD!E3 | C3: =BD!F3 | D3: =BD!H3 | E3: =(DateEval-C3)/365.25 | F3: =(DateEval-B3)/365.25 | G3: =TRUNC(F3) | H3: =EDATE(B3,12*AgeRetraite) | I3: =MAX((H3-DateEval)/365.25,0) | J3: =D3/12*(1+TxSal)^MAX(AgeRetraite-G3,0) | K3: =E3+I3 | L3: =(VLOOKUP(TRUNC(K3),Baremes!$A:$C,3,TRUE)+(K3-TRUNC(K3))*VLOOKUP(TRUNC(K3)+1,Baremes!$A:$B,2,TRUE))*J3 | M3: =IF(G3<AgeRetraite,VLOOKUP(AgeRetraite,Table_CIMA_H!$A:$B,2,TRUE)/VLOOKUP(G3,Table_CIMA_H!$A:$B,2,TRUE),1) | N3: =1 | O3: =1/(1+TauxTech)^(I3+0.5) | P3: =L3*M3*N3*O3 | Q3: =P3*E3/K3 | R3: =P3/K3 | S3: =IF(I3<=0,0,VLOOKUP(TRUNC(E3),Baremes!$A:$C,3,TRUE)*D3/12) | T3: =IF(I3<=0,0,S3*TxLic*(1-((1-TxTurnover)/(1+TauxTech))^I3)/(1-(1-TxTurnover)/(1+TauxTech))) | U3: =D3/24 | V3: =IF(I3<=0,0,VLOOKUP(TRUNC(E3),Baremes!$A:$C,3,TRUE)*U3) | W3: =S3+V3 | X3: =(VLOOKUP(G3,Table_CIMA_H!$A:$B,2,TRUE)-VLOOKUP(G3+1,Table_CIMA_H!$A:$B,2,TRUE))/VLOOKUP(G3,Table_CIMA_H!$A:$B,2,TRUE) | Y3: =W3*X3
A4: =BD!A4 | B4: =BD!E4 | C4: =BD!F4 | D4: =BD!H4 | E4: =(DateEval-C4)/365.25 | F4: =(DateEval-B4)/365.25 | G4: =TRUNC(F4) | H4: =EDATE(B4,12*AgeRetraite) | I4: =MAX((H4-DateEval)/365.25,0) | J4: =D4/12*(1+TxSal)^MAX(AgeRetraite-G4,0) | K4: =E4+I4 | L4: =(VLOOKUP(TRUNC(K4),Baremes!$A:$C,3,TRUE)+(K4-TRUNC(K4))*VLOOKUP(TRUNC(K4)+1,Baremes!$A:$B,2,TRUE))*J4 | M4: =IF(G4<AgeRetraite,VLOOKUP(AgeRetraite,Table_CIMA_H!$A:$B,2,TRUE)/VLOOKUP(G4,Table_CIMA_H!$A:$B,2,TRUE),1) | N4: =1 | O4: =1/(1+TauxTech)^(I4+0.5) | P4: =L4*M4*N4*O4 | Q4: =P4*E4/K4 | R4: =P4/K4 | S4: =IF(I4<=0,0,VLOOKUP(TRUNC(E4),Baremes!$A:$C,3,TRUE)*D4/12) | T4: =IF(I4<=0,0,S4*TxLic*(1-((1-TxTurnover)/(1+TauxTech))^I4)/(1-(1-TxTurnover)/(1+TauxTech))) | U4: =D4/24 | V4: =IF(I4<=0,0,VLOOKUP(TRUNC(E4),Baremes!$A:$C,3,TRUE)*U4) | W4: =S4+V4 | X4: =(VLOOKUP(G4,Table_CIMA_H!$A:$B,2,TRUE)-VLOOKUP(G4+1,Table_CIMA_H!$A:$B,2,TRUE))/VLOOKUP(G4,Table_CIMA_H!$A:$B,2,TRUE) | Y4: =W4*X4
A5: =BD!A5 | B5: =BD!E5 | C5: =BD!F5 | D5: =BD!H5 | E5: =(DateEval-C5)/365.25 | F5: =(DateEval-B5)/365.25 | G5: =TRUNC(F5) | H5: =EDATE(B5,12*AgeRetraite) | I5: =MAX((H5-DateEval)/365.25,0) | J5: =D5/12*(1+TxSal)^MAX(AgeRetraite-G5,0) | K5: =E5+I5 | L5: =(VLOOKUP(TRUNC(K5),Baremes!$A:$C,3,TRUE)+(K5-TRUNC(K5))*VLOOKUP(TRUNC(K5)+1,Baremes!$A:$B,2,TRUE))*J5 | M5: =IF(G5<AgeRetraite,VLOOKUP(AgeRetraite,Table_CIMA_H!$A:$B,2,TRUE)/VLOOKUP(G5,Table_CIMA_H!$A:$B,2,TRUE),1) | N5: =1 | O5: =1/(1+TauxTech)^(I5+0.5) | P5: =L5*M5*N5*O5 | Q5: =P5*E5/K5 | R5: =P5/K5 | S5: =IF(I5<=0,0,VLOOKUP(TRUNC(E5),Baremes!$A:$C,3,TRUE)*D5/12) | T5: =IF(I5<=0,0,S5*TxLic*(1-((1-TxTurnover)/(1+TauxTech))^I5)/(1-(1-TxTurnover)/(1+TauxTech))) | U5: =D5/24 | V5: =IF(I5<=0,0,VLOOKUP(TRUNC(E5),Baremes!$A:$C,3,TRUE)*U5) | W5: =S5+V5 | X5: =(VLOOKUP(G5,Table_CIMA_H!$A:$B,2,TRUE)-VLOOKUP(G5+1,Table_CIMA_H!$A:$B,2,TRUE))/VLOOKUP(G5,Table_CIMA_H!$A:$B,2,TRUE) | Y5: =W5*X5
A6: =BD!A6 | B6: =BD!E6 | C6: =BD!F6 | D6: =BD!H6 | E6: =(DateEval-C6)/365.25 | F6: =(DateEval-B6)/365.25 | G6: =TRUNC(F6) | H6: =EDATE(B6,12*AgeRetraite) | I6: =MAX((H6-DateEval)/365.25,0) | J6: =D6/12*(1+TxSal)^MAX(AgeRetraite-G6,0) | K6: =E6+I6 | L6: =(VLOOKUP(TRUNC(K6),Baremes!$A:$C,3,TRUE)+(K6-TRUNC(K6))*VLOOKUP(TRUNC(K6)+1,Baremes!$A:$B,2,TRUE))*J6 | M6: =IF(G6<AgeRetraite,VLOOKUP(AgeRetraite,Table_CIMA_H!$A:$B,2,TRUE)/VLOOKUP(G6,Table_CIMA_H!$A:$B,2,TRUE),1) | N6: =1 | O6: =1/(1+TauxTech)^(I6+0.5) | P6: =L6*M6*N6*O6 | Q6: =P6*E6/K6 | R6: =P6/K6 | S6: =IF(I6<=0,0,VLOOKUP(TRUNC(E6),Baremes!$A:$C,3,TRUE)*D6/12) | T6: =IF(I6<=0,0,S6*TxLic*(1-((1-TxTurnover)/(1+TauxTech))^I6)/(1-(1-TxTurnover)/(1+TauxTech))) | U6: =D6/24 | V6: =IF(I6<=0,0,VLOOKUP(TRUNC(E6),Baremes!$A:$C,3,TRUE)*U6) | W6: =S6+V6 | X6: =(VLOOKUP(G6,Table_CIMA_H!$A:$B,2,TRUE)-VLOOKUP(G6+1,Table_CIMA_H!$A:$B,2,TRUE))/VLOOKUP(G6,Table_CIMA_H!$A:$B,2,TRUE) | Y6: =W6*X6
A7: =BD!A7 | B7: =BD!E7 | C7: =BD!F7 | D7: =BD!H7 | E7: =(DateEval-C7)/365.25 | F7: =(DateEval-B7)/365.25 | G7: =TRUNC(F7) | H7: =EDATE(B7,12*AgeRetraite) | I7: =MAX((H7-DateEval)/365.25,0) | J7: =D7/12*(1+TxSal)^MAX(AgeRetraite-G7,0) | K7: =E7+I7 | L7: =(VLOOKUP(TRUNC(K7),Baremes!$A:$C,3,TRUE)+(K7-TRUNC(K7))*VLOOKUP(TRUNC(K7)+1,Baremes!$A:$B,2,TRUE))*J7 | M7: =IF(G7<AgeRetraite,VLOOKUP(AgeRetraite,Table_CIMA_H!$A:$B,2,TRUE)/VLOOKUP(G7,Table_CIMA_H!$A:$B,2,TRUE),1) | N7: =1 | O7: =1/(1+TauxTech)^(I7+0.5) | P7: =L7*M7*N7*O7 | Q7: =P7*E7/K7 | R7: =P7/K7 | S7: =IF(I7<=0,0,VLOOKUP(TRUNC(E7),Baremes!$A:$C,3,TRUE)*D7/12) | T7: =IF(I7<=0,0,S7*TxLic*(1-((1-TxTurnover)/(1+TauxTech))^I7)/(1-(1-TxTurnover)/(1+TauxTech))) | U7: =D7/24 | V7: =IF(I7<=0,0,VLOOKUP(TRUNC(E7),Baremes!$A:$C,3,TRUE)*U7) | W7: =S7+V7 | X7: =(VLOOKUP(G7,Table_CIMA_H!$A:$B,2,TRUE)-VLOOKUP(G7+1,Table_CIMA_H!$A:$B,2,TRUE))/VLOOKUP(G7,Table_CIMA_H!$A:$B,2,TRUE) | Y7: =W7*X7
A8: =BD!A8 | B8: =BD!E8 | C8: =BD!F8 | D8: =BD!H8 | E8: =(DateEval-C8)/365.25 | F8: =(DateEval-B8)/365.25 | G8: =TRUNC(F8) | H8: =EDATE(B8,12*AgeRetraite) | I8: =MAX((H8-DateEval)/365.25,0) | J8: =D8/12*(1+TxSal)^MAX(AgeRetraite-G8,0) | K8: =E8+I8 | L8: =(VLOOKUP(TRUNC(K8),Baremes!$A:$C,3,TRUE)+(K8-TRUNC(K8))*VLOOKUP(TRUNC(K8)+1,Baremes!$A:$B,2,TRUE))*J8 | M8: =IF(G8<AgeRetraite,VLOOKUP(AgeRetraite,Table_CIMA_H!$A:$B,2,TRUE)/VLOOKUP(G8,Table_CIMA_H!$A:$B,2,TRUE),1) | N8: =1 | O8: =1/(1+TauxTech)^(I8+0.5) | P8: =L8*M8*N8*O8 | Q8: =P8*E8/K8 | R8: =P8/K8 | S8: =IF(I8<=0,0,VLOOKUP(TRUNC(E8),Baremes!$A:$C,3,TRUE)*D8/12) | T8: =IF(I8<=0,0,S8*TxLic*(1-((1-TxTurnover)/(1+TauxTech))^I8)/(1-(1-TxTurnover)/(1+TauxTech))) | U8: =D8/24 | V8: =IF(I8<=0,0,VLOOKUP(TRUNC(E8),Baremes!$A:$C,3,TRUE)*U8) | W8: =S8+V8 | X8: =(VLOOKUP(G8,Table_CIMA_H!$A:$B,2,TRUE)-VLOOKUP(G8+1,Table_CIMA_H!$A:$B,2,TRUE))/VLOOKUP(G8,Table_CIMA_H!$A:$B,2,TRUE) | Y8: =W8*X8
A9: =BD!A9 | B9: =BD!E9 | C9: =BD!F9 | D9: =BD!H9 | E9: =(DateEval-C9)/365.25 | F9: =(DateEval-B9)/365.25 | G9: =TRUNC(F9) | H9: =EDATE(B9,12*AgeRetraite) | I9: =MAX((H9-DateEval)/365.25,0) | J9: =D9/12*(1+TxSal)^MAX(AgeRetraite-G9,0) | K9: =E9+I9 | L9: =(VLOOKUP(TRUNC(K9),Baremes!$A:$C,3,TRUE)+(K9-TRUNC(K9))*VLOOKUP(TRUNC(K9)+1,Baremes!$A:$B,2,TRUE))*J9 | M9: =IF(G9<AgeRetraite,VLOOKUP(AgeRetraite,Table_CIMA_H!$A:$B,2,TRUE)/VLOOKUP(G9,Table_CIMA_H!$A:$B,2,TRUE),1) | N9: =1 | O9: =1/(1+TauxTech)^(I9+0.5) | P9: =L9*M9*N9*O9 | Q9: =P9*E9/K9 | R9: =P9/K9 | S9: =IF(I9<=0,0,VLOOKUP(TRUNC(E9),Baremes!$A:$C,3,TRUE)*D9/12) | T9: =IF(I9<=0,0,S9*TxLic*(1-((1-TxTurnover)/(1+TauxTech))^I9)/(1-(1-TxTurnover)/(1+TauxTech))) | U9: =D9/24 | V9: =IF(I9<=0,0,VLOOKUP(TRUNC(E9),Baremes!$A:$C,3,TRUE)*U9) | W9: =S9+V9 | X9: =(VLOOKUP(G9,Table_CIMA_H!$A:$B,2,TRUE)-VLOOKUP(G9+1,Table_CIMA_H!$A:$B,2,TRUE))/VLOOKUP(G9,Table_CIMA_H!$A:$B,2,TRUE) | Y9: =W9*X9
A10: =BD!A10 | B10: =BD!E10 | C10: =BD!F10 | D10: =BD!H10 | E10: =(DateEval-C10)/365.25 | F10: =(DateEval-B10)/365.25 | G10: =TRUNC(F10) | H10: =EDATE(B10,12*AgeRetraite) | I10: =MAX((H10-DateEval)/365.25,0) | J10: =D10/12*(1+TxSal)^MAX(AgeRetraite-G10,0) | K10: =E10+I10 | L10: =(VLOOKUP(TRUNC(K10),Baremes!$A:$C,3,TRUE)+(K10-TRUNC(K10))*VLOOKUP(TRUNC(K10)+1,Baremes!$A:$B,2,TRUE))*J10 | M10: =IF(G10<AgeRetraite,VLOOKUP(AgeRetraite,Table_CIMA_H!$A:$B,2,TRUE)/VLOOKUP(G10,Table_CIMA_H!$A:$B,2,TRUE),1) | N10: =1 | O10: =1/(1+TauxTech)^(I10+0.5) | P10: =L10*M10*N10*O10 | Q10: =P10*E10/K10 | R10: =P10/K10 | S10: =IF(I10<=0,0,VLOOKUP(TRUNC(E10),Baremes!$A:$C,3,TRUE)*D10/12) | T10: =IF(I10<=0,0,S10*TxLic*(1-((1-TxTurnover)/(1+TauxTech))^I10)/(1-(1-TxTurnover)/(1+TauxTech))) | U10: =D10/24 | V10: =IF(I10<=0,0,VLOOKUP(TRUNC(E10),Baremes!$A:$C,3,TRUE)*U10) | W10: =S10+V10 | X10: =(VLOOKUP(G10,Table_CIMA_H!$A:$B,2,TRUE)-VLOOKUP(G10+1,Table_CIMA_H!$A:$B,2,TRUE))/VLOOKUP(G10,Table_CIMA_H!$A:$B,2,TRUE) | Y10: =W10*X10
A11: =BD!A11 | B11: =BD!E11 | C11: =BD!F11 | D11: =BD!H11 | E11: =(DateEval-C11)/365.25 | F11: =(DateEval-B11)/365.25 | G11: =TRUNC(F11) | H11: =EDATE(B11,12*AgeRetraite) | I11: =MAX((H11-DateEval)/365.25,0) | J11: =D11/12*(1+TxSal)^MAX(AgeRetraite-G11,0) | K11: =E11+I11 | L11: =(VLOOKUP(TRUNC(K11),Baremes!$A:$C,3,TRUE)+(K11-TRUNC(K11))*VLOOKUP(TRUNC(K11)+1,Baremes!$A:$B,2,TRUE))*J11 | M11: =IF(G11<AgeRetraite,VLOOKUP(AgeRetraite,Table_CIMA_H!$A:$B,2,TRUE)/VLOOKUP(G11,Table_CIMA_H!$A:$B,2,TRUE),1) | N11: =1 | O11: =1/(1+TauxTech)^(I11+0.5) | P11: =L11*M11*N11*O11 | Q11: =P11*E11/K11 | R11: =P11/K11 | S11: =IF(I11<=0,0,VLOOKUP(TRUNC(E11),Baremes!$A:$C,3,TRUE)*D11/12) | T11: =IF(I11<=0,0,S11*TxLic*(1-((1-TxTurnover)/(1+TauxTech))^I11)/(1-(1-TxTurnover)/(1+TauxTech))) | U11: =D11/24 | V11: =IF(I11<=0,0,VLOOKUP(TRUNC(E11),Baremes!$A:$C,3,TRUE)*U11) | W11: =S11+V11 | X11: =(VLOOKUP(G11,Table_CIMA_H!$A:$B,2,TRUE)-VLOOKUP(G11+1,Table_CIMA_H!$A:$B,2,TRUE))/VLOOKUP(G11,Table_CIMA_H!$A:$B,2,TRUE) | Y11: =W11*X11
A12: =BD!A12 | B12: =BD!E12 | C12: =BD!F12 | D12: =BD!H12 | E12: =(DateEval-C12)/365.25 | F12: =(DateEval-B12)/365.25 | G12: =TRUNC(F12) | H12: =EDATE(B12,12*AgeRetraite) | I12: =MAX((H12-DateEval)/365.25,0) | J12: =D12/12*(1+TxSal)^MAX(AgeRetraite-G12,0) | K12: =E12+I12 | L12: =(VLOOKUP(TRUNC(K12),Baremes!$A:$C,3,TRUE)+(K12-TRUNC(K12))*VLOOKUP(TRUNC(K12)+1,Baremes!$A:$B,2,TRUE))*J12 | M12: =IF(G12<AgeRetraite,VLOOKUP(AgeRetraite,Table_CIMA_H!$A:$B,2,TRUE)/VLOOKUP(G12,Table_CIMA_H!$A:$B,2,TRUE),1) | N12: =1 | O12: =1/(1+TauxTech)^(I12+0.5) | P12: =L12*M12*N12*O12 | Q12: =P12*E12/K12 | R12: =P12/K12 | S12: =IF(I12<=0,0,VLOOKUP(TRUNC(E12),Baremes!$A:$C,3,TRUE)*D12/12) | T12: =IF(I12<=0,0,S12*TxLic*(1-((1-TxTurnover)/(1+TauxTech))^I12)/(1-(1-TxTurnover)/(1+TauxTech))) | U12: =D12/24 | V12: =IF(I12<=0,0,VLOOKUP(TRUNC(E12),Baremes!$A:$C,3,TRUE)*U12) | W12: =S12+V12 | X12: =(VLOOKUP(G12,Table_CIMA_H!$A:$B,2,TRUE)-VLOOKUP(G12+1,Table_CIMA_H!$A:$B,2,TRUE))/VLOOKUP(G12,Table_CIMA_H!$A:$B,2,TRUE) | Y12: =W12*X12
A13: =BD!A13 | B13: =BD!E13 | C13: =BD!F13 | D13: =BD!H13 | E13: =(DateEval-C13)/365.25 | F13: =(DateEval-B13)/365.25 | G13: =TRUNC(F13) | H13: =EDATE(B13,12*AgeRetraite) | I13: =MAX((H13-DateEval)/365.25,0) | J13: =D13/12*(1+TxSal)^MAX(AgeRetraite-G13,0) | K13: =E13+I13 | L13: =(VLOOKUP(TRUNC(K13),Baremes!$A:$C,3,TRUE)+(K13-TRUNC(K13))*VLOOKUP(TRUNC(K13)+1,Baremes!$A:$B,2,TRUE))*J13 | M13: =IF(G13<AgeRetraite,VLOOKUP(AgeRetraite,Table_CIMA_H!$A:$B,2,TRUE)/VLOOKUP(G13,Table_CIMA_H!$A:$B,2,TRUE),1) | N13: =1 | O13: =1/(1+TauxTech)^(I13+0.5) | P13: =L13*M13*N13*O13 | Q13: =P13*E13/K13 | R13: =P13/K13 | S13: =IF(I13<=0,0,VLOOKUP(TRUNC(E13),Baremes!$A:$C,3,TRUE)*D13/12) | T13: =IF(I13<=0,0,S13*TxLic*(1-((1-TxTurnover)/(1+TauxTech))^I13)/(1-(1-TxTurnover)/(1+TauxTech))) | U13: =D13/24 | V13: =IF(I13<=0,0,VLOOKUP(TRUNC(E13),Baremes!$A:$C,3,TRUE)*U13) | W13: =S13+V13 | X13: =(VLOOKUP(G13,Table_CIMA_H!$A:$B,2,TRUE)-VLOOKUP(G13+1,Table_CIMA_H!$A:$B,2,TRUE))/VLOOKUP(G13,Table_CIMA_H!$A:$B,2,TRUE) | Y13: =W13*X13
... A51: =BD!A51 | B51: =BD!E51 | C51: =BD!F51 | D51: =BD!H51 | E51: =(DateEval-C51)/365.25 | F51: =(DateEval-B51)/365.25 | G51: =TRUNC(F51) | H51: =EDATE(B51,12*AgeRetraite) | I51: =MAX((H51-DateEval)/365.25,0) | J51: =D51/12*(1+TxSal)^MAX(AgeRetraite-G51,0) | K51: =E51+I51 | L51: =(VLOOKUP(TRUNC(K51),Baremes!$A:$C,3,TRUE)+(K51-TRUNC(K51))*VLOOKUP(TRUNC(K51)+1,Baremes!$A:$B,2,TRUE))*J51 | M51: =IF(G51<AgeRetraite,VLOOKUP(AgeRetraite,Table_CIMA_H!$A:$B,2,TRUE)/VLOOKUP(G51,Table_CIMA_H!$A:$B,2,TRUE),1) | N51: =1 | O51: =1/(1+TauxTech)^(I51+0.5) | P51: =L51*M51*N51*O51 | Q51: =P51*E51/K51 | R51: =P51/K51 | S51: =IF(I51<=0,0,VLOOKUP(TRUNC(E51),Baremes!$A:$C,3,TRUE)*D51/12) | T51: =IF(I51<=0,0,S51*TxLic*(1-((1-TxTurnover)/(1+TauxTech))^I51)/(1-(1-TxTurnover)/(1+TauxTech))) | U51: =D51/24 | V51: =IF(I51<=0,0,VLOOKUP(TRUNC(E51),Baremes!$A:$C,3,TRUE)*U51) | W51: =S51+V51 | X51: =(VLOOKUP(G51,Table_CIMA_H!$A:$B,2,TRUE)-VLOOKUP(G51+1,Table_CIMA_H!$A:$B,2,TRUE))/VLOOKUP(G51,Table_CIMA_H!$A:$B,2,TRUE) | Y51: =W51*X51
A52: TOTAL | D52: =SUM(D2:D51) | P52: =SUM(P2:P51) | Q52: =SUM(Q2:Q51) | R52: =SUM(R2:R51) | S52: =SUM(S2:S51) | T52: =SUM(T2:T51) | W52: =SUM(W2:W51) | Y52: =SUM(Y2:Y51)

Sheet Resultats
A1: SYNTHÈSE DE L'ÉVALUATION AU 31/12/2025 — SENIA S.A.
A3: STATISTIQUES DU GROUPE
A4: Effectif | B4: =COUNT(Calculs!A2:A51)
A5: Masse salariale annuelle (FCFA) | B5: =SUM(Calculs!$D$2:$D$51)
A6: Âge moyen du groupe (années) | B6: =AVERAGE(Calculs!F2:F51)
A7: Ancienneté moyenne (années) | B7: =AVERAGE(Calculs!E2:E51)
A8: Durée résiduelle moyenne d'activité (années) | B8: =AVERAGE(Calculs!I2:I51)
A10: RÉSULTATS IFC (FCFA)
A11: Engagement global (VP des prestations futures) | B11: =SUM(Calculs!P2:P51)
A12: Dette actuarielle | B12: =SUM(Calculs!Q2:Q51)
A13: Charge normale de l'exercice | B13: =SUM(Calculs!R2:R51)
A14: Passif de l'indemnité de licenciement | B14: =SUM(Calculs!T2:T51)
A16: MODALITÉS DE FINANCEMENT
A17: Option 1 — Prime unique (engagement global + passif IL) | B17: =B11+B14
A18: Option 2 — Prime initiale (dette actuarielle), puis charge normale annuelle | B18: =B12
A19: dont charge normale de l'exercice suivant | B19: =B13
A20: Option 3 — Amortissement de la dette actuarielle (par an) | B20: =B12/DureeAmort
A21: Option 3 — Prime annuelle sur la durée d'amortissement | B21: =B20+B13
A22: Taux de prime uniforme (en % de la masse salariale) | B22: =B21/SUM(Calculs!$D$2:$D$51)
A24: RÉSULTATS IFC+ (couverture décès, FCFA)
A25: Capitaux garantis (indemnités décès CCNI) | B25: =SUM(Calculs!W2:W51)
A26: Prime pure annuelle | B26: =SUM(Calculs!Y2:Y51)
A27: Prime commerciale annuelle (chargée) | B27: =B26/(1-FraisIFCP)
A28: Taux de prime sur les capitaux garantis | B28: =B27/B25
A29: Taux de prime sur la masse salariale | B29: =B27/SUM(Calculs!$D$2:$D$51)
