Workbook

Sheet Tableau d'amortissement
A1: Tableau d'amortissement
A3: Caractéristiques de l'emprunt
A4: Montant emprunté | B4: 200000 | I4: taux de chargement annuel | J4: 0.035
A5: Taux d'interet annuel | B5: 0.033 | I5: taux de chargement mensuel | J5: =-1+(1+J4)^(1/12) -> 0.0028708987
A6: Durée | B6: 10 | C6: ans | I6: âge assuré 1 | J6: 24
A7: Date de début | B7: 45383 | C7: JJ/MM/YYYY | I7: âge assuré 2 | J7: 28
A9: Vue globale de l'emprunt
A10: Nombre de mensualités | B10: =B6*12 -> 120
A11: Montant mensuel | B11: =PMT(-1+(1+B5)^(1/12),B10,-B4) -> 1954.4843
A12: Total versements | B12: =B11*B10 -> 234538.12
A13: Cout de l'emprunt | B13: =B12-B4 -> 34538.115
C16: Echéance | D16: Date | E16: Capital amorti | F16: Mensuallité | G16: Details remboursement | I16: Capital Restant dû | J16: Prime
G17: Interets | H17: Capital
C18: 1 | D18: =EOMONTH(B7,0) -> 45412 | E18: =B4 -> 200000 | F18: =IF(C18="","",$B$11) -> 1954.4843 | G18: =IF(C18="","",E18*(-1+(1+$B$5)^(1/12))) -> 541.85252 | H18: =IF(C18="","",F18-G18) -> 1412.6318 | I18: =IF(C18="","",E18-H18) -> 198587.37 | J18: =IF(C18="","",I18*VLOOKUP(J6,'table CIMA'!A1:F112,2,FALSE)/VLOOKUP(J6,'table CIMA'!A1:F112,2,FALSE)) -> 198587.37
C19: =IFERROR(IF(C18+1<=$B$10,C18+1,""),"") -> 2 | D19: =IF(C19="","",EOMONTH(D18,1)) -> 45443 | E19: =IF(C19="","",I18) -> 198587.37 | F19: =IF(C19="","",$B$11) -> 1954.4843 | G19: =IF(C19="","",E19*(-1+(1+$B$5)^(1/12))) -> 538.02533 | H19: =IF(C19="","",F19-G19) -> 1416.459 | I19: =IF(C19="","",E19-H19) -> 197170.91
C20: =IFERROR(IF(C19+1<=$B$10,C19+1,""),"") -> 3 | D20: =IF(C20="","",EOMONTH(D19,1)) -> 45473 | E20: =IF(C20="","",I19) -> 197170.91 | F20: =IF(C20="","",$B$11) -> 1954.4843 | G20: =IF(C20="","",E20*(-1+(1+$B$5)^(1/12))) -> 534.18777 | H20: =IF(C20="","",F20-G20) -> 1420.2965 | I20: =IF(C20="","",E20-H20) -> 195750.61
C21: =IFERROR(IF(C20+1<=$B$10,C20+1,""),"") -> 4 | D21: =IF(C21="","",EOMONTH(D20,1)) -> 45504 | E21: =IF(C21="","",I20) -> 195750.61 | F21: =IF(C21="","",$B$11) -> 1954.4843 | G21: =IF(C21="","",E21*(-1+(1+$B$5)^(1/12))) -> 530.33982 | H21: =IF(C21="","",F21-G21) -> 1424.1445 | I21: =IF(C21="","",E21-H21) -> 194326.47
C22: =IFERROR(IF(C21+1<=$B$10,C21+1,""),"") -> 5 | D22: =IF(C22="","",EOMONTH(D21,1)) -> 45535 | E22: =IF(C22="","",I21) -> 194326.47 | F22: =IF(C22="","",$B$11) -> 1954.4843 | G22: =IF(C22="","",E22*(-1+(1+$B$5)^(1/12))) -> 526.48144 | H22: =IF(C22="","",F22-G22) -> 1428.0029 | I22: =IF(C22="","",E22-H22) -> 192898.47
C23: =IFERROR(IF(C22+1<=$B$10,C22+1,""),"") -> 6 | D23: =IF(C23="","",EOMONTH(D22,1)) -> 45565 | E23: =IF(C23="","",I22) -> 192898.47 | F23: =IF(C23="","",$B$11) -> 1954.4843 | G23: =IF(C23="","",E23*(-1+(1+$B$5)^(1/12))) -> 522.6126 | H23: =IF(C23="","",F23-G23) -> 1431.8717 | I23: =IF(C23="","",E23-H23) -> 191466.59
C24: =IFERROR(IF(C23+1<=$B$10,C23+1,""),"") -> 7 | D24: =IF(C24="","",EOMONTH(D23,1)) -> 45596 | E24: =IF(C24="","",I23) -> 191466.59 | F24: =IF(C24="","",$B$11) -> 1954.4843 | G24: =IF(C24="","",E24*(-1+(1+$B$5)^(1/12))) -> 518.73328 | H24: =IF(C24="","",F24-G24) -> 1435.751 | I24: =IF(C24="","",E24-H24) -> 190030.84
C25: =IFERROR(IF(C24+1<=$B$10,C24+1,""),"") -> 8 | D25: =IF(C25="","",EOMONTH(D24,1)) -> 45626 | E25: =IF(C25="","",I24) -> 190030.84 | F25: =IF(C25="","",$B$11) -> 1954.4843 | G25: =IF(C25="","",E25*(-1+(1+$B$5)^(1/12))) -> 514.84346 | H25: =IF(C25="","",F25-G25) -> 1439.6408 | I25: =IF(C25="","",E25-H25) -> 188591.2
C26: =IFERROR(IF(C25+1<=$B$10,C25+1,""),"") -> 9 | D26: =IF(C26="","",EOMONTH(D25,1)) -> 45657 | E26: =IF(C26="","",I25) -> 188591.2 | F26: =IF(C26="","",$B$11) -> 1954.4843 | G26: =IF(C26="","",E26*(-1+(1+$B$5)^(1/12))) -> 510.94309 | H26: =IF(C26="","",F26-G26) -> 1443.5412 | I26: =IF(C26="","",E26-H26) -> 187147.66
C27: =IFERROR(IF(C26+1<=$B$10,C26+1,""),"") -> 10 | D27: =IF(C27="","",EOMONTH(D26,1)) -> 45688 | E27: =IF(C27="","",I26) -> 187147.66 | F27: =IF(C27="","",$B$11) -> 1954.4843 | G27: =IF(C27="","",E27*(-1+(1+$B$5)^(1/12))) -> 507.03216 | H27: =IF(C27="","",F27-G27) -> 1447.4521 | I27: =IF(C27="","",E27-H27) -> 185700.21
C28: =IFERROR(IF(C27+1<=$B$10,C27+1,""),"") -> 11 | D28: =IF(C28="","",EOMONTH(D27,1)) -> 45716 | E28: =IF(C28="","",I27) -> 185700.21 | F28: =IF(C28="","",$B$11) -> 1954.4843 | G28: =IF(C28="","",E28*(-1+(1+$B$5)^(1/12))) -> 503.11063 | H28: =IF(C28="","",F28-G28) -> 1451.3737 | I28: =IF(C28="","",E28-H28) -> 184248.83
C29: =IFERROR(IF(C28+1<=$B$10,C28+1,""),"") -> 12 | D29: =IF(C29="","",EOMONTH(D28,1)) -> 45747 | E29: =IF(C29="","",I28) -> 184248.83 | F29: =IF(C29="","",$B$11) -> 1954.4843 | G29: =IF(C29="","",E29*(-1+(1+$B$5)^(1/12))) -> 499.17848 | H29: =IF(C29="","",F29-G29) -> 1455.3058 | I29: =IF(C29="","",E29-H29) -> 182793.53
C30: =IFERROR(IF(C29+1<=$B$10,C29+1,""),"") -> 13 | D30: =IF(C30="","",EOMONTH(D29,1)) -> 45777 | E30: =IF(C30="","",I29) -> 182793.53 | F30: =IF(C30="","",$B$11) -> 1954.4843 | G30: =IF(C30="","",E30*(-1+(1+$B$5)^(1/12))) -> 495.23567 | H30: =IF(C30="","",F30-G30) -> 1459.2486 | I30: =IF(C30="","",E30-H30) -> 181334.28
... C558: =IFERROR(IF(C557+1<=$B$10,C557+1,""),"") | D558: =IF(C558="","",EOMONTH(D557,1)) | E558: =IF(C558="","",I557) | F558: =IF(C558="","",$B$11) | G558: =IF(C558="","",E558*(-1+(1+$B$5)^(1/12))) | H558: =IF(C558="","",F558-G558) | I558: =IF(C558="","",E558-H558)

Sheet Calcul de prime
A1: Tableau de calcul des primes
A3: Caractéristiques de l'emprunt
A4: Montant emprunté | B4: 50000000 | H4: taux de chargement annuel | I4: 0.035
A5: Taux d'interet annuel | B5: 0.07 | H5: taux technique | I5: 0.035
A6: Durée | B6: 10 | C6: ans | H6: âge assuré 1 | I6: 24 | J6: =MAX(I6:I7) -> 28
A7: Date de début | B7: 45383 | C7: JJ/MM/YYYY | H7: âge assuré 2 | I7: 28
H8: Engagement assureur | I8: =SUM(I17:I557) -> 520994.47
A9: Vue globale de l'emprunt | H9: Taux de prime | I9: =I8/SUM(J17:J557) -> 0.0020733824
A10: Montant annuel | B10: =PMT(B5,B6,-B4) -> 7118875.1 | H10: Engagement assuré | I10: =SUM(K17:K557) -> 520994.47
A11: Total versements | B11: =B10*B6 -> 71188751
A12: Cout de l'emprunt | B12: =B11-B4 -> 21188751
C15: Echéance | D15: Capital amorti | E15: Annualité | F15: Details remboursement | H15: Capital Restant dû | I15: Engagement périodique | J15: Y | K15: Primes
F16: Interets | G16: Capital
C17: 1 | D17: =B4 -> 50000000 | E17: =IF(C17="","",$B$10) -> 7118875.1 | F17: =IF(C17="","",D17*$B$5) -> 3500000 | G17: =IF(C17="","",E17-F17) -> 3618875.1 | H17: =IF(C17="","",D17-G17) -> 46381125 | I17: =IF(C17="","",H17*(VLOOKUP($J$6+C17-1,'table CIMA'!$A$1:$H$112,2)/(VLOOKUP($J$6,'table CIMA'!$A$1:$H$112,2)))*VLOOKUP($J$6+C17,'table CIMA'!$A$1:$H$112,8)/(1+$J$4)^(C17-1+0.5)) -> 87875.203 | J17: =IF(C17="","",H17*(VLOOKUP($J$6+C17-1,'table CIMA'!$A$1:$H$112,2)/(VLOOKUP($J$6,'table CIMA'!$A$1:$H$112,2)))/(1+$J$4)^(C17-1)) -> 46381125 | K17: =IF(C17="","",J17*$I$9) -> 96165.806
C18: =IFERROR(IF(C17+1<=$B$6,C17+1,""),"") -> 2 | D18: =IF(C18="","",H17) -> 46381125 | E18: =IF(C18="","",$B$10) -> 7118875.1 | F18: =IF(C18="","",D18*$B$5) -> 3246678.7 | G18: =IF(C18="","",E18-F18) -> 3872196.4 | H18: =IF(C18="","",D18-G18) -> 42508928 | I18: =IF(C18="","",H18*(VLOOKUP($J$6+C18-1,'table CIMA'!$A$1:$H$112,2)/(VLOOKUP($J$6,'table CIMA'!$A$1:$H$112,2)))*VLOOKUP($J$6+C18,'table CIMA'!$A$1:$H$112,8)/(1+$J$4)^(C18-1+0.5)) -> 82643.074 | J18: =IF(C18="","",H18*(VLOOKUP($J$6+C18-1,'table CIMA'!$A$1:$H$112,2)/(VLOOKUP($J$6,'table CIMA'!$A$1:$H$112,2)))/(1+$J$4)^(C18-1)) -> 42428390 | K18: =IF(C18="","",J18*$I$9) -> 87970.275
C19: =IFERROR(IF(C18+1<=$B$6,C18+1,""),"") -> 3 | D19: =IF(C19="","",H18) -> 42508928 | E19: =IF(C19="","",$B$10) -> 7118875.1 | F19: =IF(C19="","",D19*$B$5) -> 2975625 | G19: =IF(C19="","",E19-F19) -> 4143250.1 | H19: =IF(C19="","",D19-G19) -> 38365678 | I19: =IF(C19="","",H19*(VLOOKUP($J$6+C19-1,'table CIMA'!$A$1:$H$112,2)/(VLOOKUP($J$6,'table CIMA'!$A$1:$H$112,2)))*VLOOKUP($J$6+C19,'table CIMA'!$A$1:$H$112,8)/(1+$J$4)^(C19-1+0.5)) -> 76185.465 | J19: =IF(C19="","",H19*(VLOOKUP($J$6+C19-1,'table CIMA'!$A$1:$H$112,2)/(VLOOKUP($J$6,'table CIMA'!$A$1:$H$112,2)))/(1+$J$4)^(C19-1)) -> 38218401 | K19: =IF(C19="","",J19*$I$9) -> 79241.359
C20: =IFERROR(IF(C19+1<=$B$6,C19+1,""),"") -> 4 | D20: =IF(C20="","",H19) -> 38365678 | E20: =IF(C20="","",$B$10) -> 7118875.1 | F20: =IF(C20="","",D20*$B$5) -> 2685597.5 | G20: =IF(C20="","",E20-F20) -> 4433277.7 | H20: =IF(C20="","",D20-G20) -> 33932401 | I20: =IF(C20="","",H20*(VLOOKUP($J$6+C20-1,'table CIMA'!$A$1:$H$112,2)/(VLOOKUP($J$6,'table CIMA'!$A$1:$H$112,2)))*VLOOKUP($J$6+C20,'table CIMA'!$A$1:$H$112,8)/(1+$J$4)^(C20-1+0.5)) -> 68710.915 | J20: =IF(C20="","",H20*(VLOOKUP($J$6+C20-1,'table CIMA'!$A$1:$H$112,2)/(VLOOKUP($J$6,'table CIMA'!$A$1:$H$112,2)))/(1+$J$4)^(C20-1)) -> 33734760 | K20: =IF(C20="","",J20*$I$9) -> 69945.056
C21: =IFERROR(IF(C20+1<=$B$6,C20+1,""),"") -> 5 | D21: =IF(C21="","",H20) -> 33932401 | E21: =IF(C21="","",$B$10) -> 7118875.1 | F21: =IF(C21="","",D21*$B$5) -> 2375268 | G21: =IF(C21="","",E21-F21) -> 4743607.1 | H21: =IF(C21="","",D21-G21) -> 29188794 | I21: =IF(C21="","",H21*(VLOOKUP($J$6+C21-1,'table CIMA'!$A$1:$H$112,2)/(VLOOKUP($J$6,'table CIMA'!$A$1:$H$112,2)))*VLOOKUP($J$6+C21,'table CIMA'!$A$1:$H$112,8)/(1+$J$4)^(C21-1+0.5)) -> 61033.471 | J21: =IF(C21="","",H21*(VLOOKUP($J$6+C21-1,'table CIMA'!$A$1:$H$112,2)/(VLOOKUP($J$6,'table CIMA'!$A$1:$H$112,2)))/(1+$J$4)^(C21-1)) -> 28959677 | K21: =IF(C21="","",J21*$I$9) -> 60044.483
C22: =IFERROR(IF(C21+1<=$B$6,C21+1,""),"") -> 6 | D22: =IF(C22="","",H21) -> 29188794 | E22: =IF(C22="","",$B$10) -> 7118875.1 | F22: =IF(C22="","",D22*$B$5) -> 2043215.6 | G22: =IF(C22="","",E22-F22) -> 5075659.6 | H22: =IF(C22="","",D22-G22) -> 24113134 | I22: =IF(C22="","",H22*(VLOOKUP($J$6+C22-1,'table CIMA'!$A$1:$H$112,2)/(VLOOKUP($J$6,'table CIMA'!$A$1:$H$112,2)))*VLOOKUP($J$6+C22,'table CIMA'!$A$1:$H$112,8)/(1+$J$4)^(C22-1+0.5)) -> 52642.483 | J22: =IF(C22="","",H22*(VLOOKUP($J$6+C22-1,'table CIMA'!$A$1:$H$112,2)/(VLOOKUP($J$6,'table CIMA'!$A$1:$H$112,2)))/(1+$J$4)^(C22-1)) -> 23873438 | K22: =IF(C22="","",J22*$I$9) -> 49498.766
C23: =IFERROR(IF(C22+1<=$B$6,C22+1,""),"") -> 7 | D23: =IF(C23="","",H22) -> 24113134 | E23: =IF(C23="","",$B$10) -> 7118875.1 | F23: =IF(C23="","",D23*$B$5) -> 1687919.4 | G23: =IF(C23="","",E23-F23) -> 5430955.8 | H23: =IF(C23="","",D23-G23) -> 18682178 | I23: =IF(C23="","",H23*(VLOOKUP($J$6+C23-1,'table CIMA'!$A$1:$H$112,2)/(VLOOKUP($J$6,'table CIMA'!$A$1:$H$112,2)))*VLOOKUP($J$6+C23,'table CIMA'!$A$1:$H$112,8)/(1+$J$4)^(C23-1+0.5)) -> 43223.789 | J23: =IF(C23="","",H23*(VLOOKUP($J$6+C23-1,'table CIMA'!$A$1:$H$112,2)/(VLOOKUP($J$6,'table CIMA'!$A$1:$H$112,2)))/(1+$J$4)^(C23-1)) -> 18455683 | K23: =IF(C23="","",J23*$I$9) -> 38265.687
C24: =IFERROR(IF(C23+1<=$B$6,C23+1,""),"") -> 8 | D24: =IF(C24="","",H23) -> 18682178 | E24: =IF(C24="","",$B$10) -> 7118875.1 | F24: =IF(C24="","",D24*$B$5) -> 1307752.5 | G24: =IF(C24="","",E24-F24) -> 5811122.7 | H24: =IF(C24="","",D24-G24) -> 12871056 | I24: =IF(C24="","",H24*(VLOOKUP($J$6+C24-1,'table CIMA'!$A$1:$H$112,2)/(VLOOKUP($J$6,'table CIMA'!$A$1:$H$112,2)))*VLOOKUP($J$6+C24,'table CIMA'!$A$1:$H$112,8)/(1+$J$4)^(C24-1+0.5)) -> 31427.559 | J24: =IF(C24="","",H24*(VLOOKUP($J$6+C24-1,'table CIMA'!$A$1:$H$112,2)/(VLOOKUP($J$6,'table CIMA'!$A$1:$H$112,2)))/(1+$J$4)^(C24-1)) -> 12685233 | K24: =IF(C24="","",J24*$I$9) -> 26301.338
C25: =IFERROR(IF(C24+1<=$B$6,C24+1,""),"") -> 9 | D25: =IF(C25="","",H24) -> 12871056 | E25: =IF(C25="","",$B$10) -> 7118875.1 | F25: =IF(C25="","",D25*$B$5) -> 900973.89 | G25: =IF(C25="","",E25-F25) -> 6217901.2 | H25: =IF(C25="","",D25-G25) -> 6653154.3 | I25: =IF(C25="","",H25*(VLOOKUP($J$6+C25-1,'table CIMA'!$A$1:$H$112,2)/(VLOOKUP($J$6,'table CIMA'!$A$1:$H$112,2)))*VLOOKUP($J$6+C25,'table CIMA'!$A$1:$H$112,8)/(1+$J$4)^(C25-1+0.5)) -> 17252.507 | J25: =IF(C25="","",H25*(VLOOKUP($J$6+C25-1,'table CIMA'!$A$1:$H$112,2)/(VLOOKUP($J$6,'table CIMA'!$A$1:$H$112,2)))/(1+$J$4)^(C25-1)) -> 6540855.9 | K25: =IF(C25="","",J25*$I$9) -> 13561.695
C26: =IFERROR(IF(C25+1<=$B$6,C25+1,""),"") -> 10 | D26: =IF(C26="","",H25) -> 6653154.3 | E26: =IF(C26="","",$B$10) -> 7118875.1 | F26: =IF(C26="","",D26*$B$5) -> 465720.8 | G26: =IF(C26="","",E26-F26) -> 6653154.3 | H26: =IF(C26="","",D26-G26) -> -1.0244548e-08 | I26: =IF(C26="","",H26*(VLOOKUP($J$6+C26-1,'table CIMA'!$A$1:$H$112,2)/(VLOOKUP($J$6,'table CIMA'!$A$1:$H$112,2)))*VLOOKUP($J$6+C26,'table CIMA'!$A$1:$H$112,8)/(1+$J$4)^(C26-1+0.5)) -> -2.8215318e-11 | J26: =IF(C26="","",H26*(VLOOKUP($J$6+C26-1,'table CIMA'!$A$1:$H$112,2)/(VLOOKUP($J$6,'table CIMA'!$A$1:$H$112,2)))/(1+$J$4)^(C26-1)) -> -1.0045065e-08 | K26: =IF(C26="","",J26*$I$9) -> -2.0827261e-11
C27: =IFERROR(IF(C26+1<=$B$6,C26+1,""),"") | D27: =IF(C27="","",H26) | E27: =IF(C27="","",$B$10) | F27: =IF(C27="","",D27*$B$5) | G27: =IF(C27="","",E27-F27) | H27: =IF(C27="","",D27-G27) | I27: =IF(C27="","",H27*(VLOOKUP($J$6+C27-1,'table CIMA'!$A$1:$H$112,2)/(VLOOKUP($J$6,'table CIMA'!$A$1:$H$112,2)))*VLOOKUP($J$6+C27,'table CIMA'!$A$1:$H$112,8)/(1+$J$4)^(C27-1+0.5)) | J27: =IF(C27="","",H27*(VLOOKUP($J$6+C27-1,'table CIMA'!$A$1:$H$112,2)/(VLOOKUP($J$6,'table CIMA'!$A$1:$H$112,2)))/(1+$J$4)^(C27-1)) | K27: =IF(C27="","",J27*$I$9)
C28: =IFERROR(IF(C27+1<=$B$6,C27+1,""),"") | D28: =IF(C28="","",H27) | E28: =IF(C28="","",$B$10) | F28: =IF(C28="","",D28*$B$5) | G28: =IF(C28="","",E28-F28) | H28: =IF(C28="","",D28-G28) | I28: =IF(C28="","",H28*(VLOOKUP($J$6+C28-1,'table CIMA'!$A$1:$H$112,2)/(VLOOKUP($J$6,'table CIMA'!$A$1:$H$112,2)))*VLOOKUP($J$6+C28,'table CIMA'!$A$1:$H$112,8)/(1+$J$4)^(C28-1+0.5)) | J28: =IF(C28="","",H28*(VLOOKUP($J$6+C28-1,'table CIMA'!$A$1:$H$112,2)/(VLOOKUP($J$6,'table CIMA'!$A$1:$H$112,2)))/(1+$J$4)^(C28-1)) | K28: =IF(C28="","",J28*$I$9)
C29: =IFERROR(IF(C28+1<=$B$6,C28+1,""),"") | D29: =IF(C29="","",H28) | E29: =IF(C29="","",$B$10) | F29: =IF(C29="","",D29*$B$5) | G29: =IF(C29="","",E29-F29) | H29: =IF(C29="","",D29-G29) | I29: =IF(C29="","",H29*(VLOOKUP($J$6+C29-1,'table CIMA'!$A$1:$H$112,2)/(VLOOKUP($J$6,'table CIMA'!$A$1:$H$112,2)))*VLOOKUP($J$6+C29,'table CIMA'!$A$1:$H$112,8)/(1+$J$4)^(C29-1+0.5)) | J29: =IF(C29="","",H29*(VLOOKUP($J$6+C29-1,'table CIMA'!$A$1:$H$112,2)/(VLOOKUP($J$6,'table CIMA'!$A$1:$H$112,2)))/(1+$J$4)^(C29-1)) | K29: =IF(C29="","",J29*$I$9)
... C557: =IFERROR(IF(C556+1<=$B$6,C556+1,""),"") | D557: =IF(C557="","",H556) | E557: =IF(C557="","",$B$10) | F557: =IF(C557="","",D557*$B$5) | G557: =IF(C557="","",E557-F557) | H557: =IF(C557="","",D557-G557) | I557: =IF(C557="","",H557*(VLOOKUP($J$6+C557-1,'table CIMA'!$A$1:$H$112,2)/(VLOOKUP($J$6,'table CIMA'!$A$1:$H$112,2)))*VLOOKUP($J$6+C557,'table CIMA'!$A$1:$H$112,8)/(1+$J$4)^(C557-1+0.5)) | J557: =IF(C557="","",H557*(VLOOKUP($J$6+C557-1,'table CIMA'!$A$1:$H$112,2)/(VLOOKUP($J$6,'table CIMA'!$A$1:$H$112,2)))/(1+$J$4)^(C557-1)) | K557: =IF(C557="","",J557*$I$9)

Sheet table CIMA
A1: Age | B1: Lx (CIMA H) | C1: Dx | D1: Cx | E1: Nx | F1: Mx | G1: px | H1: qx
A2: 0 | B2: 1000000 | C2: 1000000 | D2: =(B2-B3)*$K$7^(A2+0.5) -> 5276.2064 | E2: =SUM(C2:$C$107) -> 26565816 | F2: =SUM(D2:$D$107) -> 103402.46 | G2: 1 | H2: =1-G2 -> 0
A3: 1 | B3: 994632.25 | C3: 960997.35 | D3: =(B3-B4)*$K$7^(A3+0.5) -> 689.56505 | E3: =SUM(C3:$C$107) -> 25565816 | F3: =SUM(D3:$D$107) -> 98126.254 | G3: =B3/B2 -> 0.99463225 | H3: =1-G3 -> 0.0053677459
A4: 2 | B4: 993906.17 | C4: 927822.05 | D4: =(B4-B5)*$K$7^(A4+0.5) -> 509.67148 | E4: =SUM(C4:$C$107) -> 24604819 | F4: =SUM(D4:$D$107) -> 97436.689 | G4: =B4/B3 -> 0.99927 | H4: =1-G4 -> 0.00073000062
A5: 3 | B5: 993350.73 | C5: 895945.44 | D5: =(B5-B6)*$K$7^(A5+0.5) -> 419.3616 | E5: =SUM(C5:$C$107) -> 23676997 | F5: =SUM(D5:$D$107) -> 96927.017 | G5: =B5/B4 -> 0.99944115 | H5: =1-G5 -> 0.00055885073
A6: 4 | B6: 992877.71 | C6: 865235.56 | D6: =(B6-B7)*$K$7^(A6+0.5) -> 346.18274 | E6: =SUM(C6:$C$107) -> 22781051 | F6: =SUM(D6:$D$107) -> 96507.655 | G6: =B6/B5 -> 0.99952381 | H6: =1-G6 -> 0.00047618671
A7: 5 | B7: 992473.56 | C7: 835636.11 | D7: =(B7-B8)*$K$7^(A7+0.5) -> 304.93869 | E7: =SUM(C7:$C$107) -> 21915816 | F7: =SUM(D7:$D$107) -> 96161.473 | G7: =B7/B6 -> 0.99959296 | H7: =1-G7 -> 0.00040704388 | J7: v= | K7: =1/(1+0.035) -> 0.96618357
A8: 6 | B8: 992105.11 | C8: 807078.14 | D8: =(B8-B9)*$K$7^(A8+0.5) -> 265.32269 | E8: =SUM(C8:$C$107) -> 21080179 | F8: =SUM(D8:$D$107) -> 95856.534 | G8: =B8/B7 -> 0.99962875 | H8: =1-G8 -> 0.00037124919
A9: 7 | B9: 991773.3 | C9: 779524.85 | D9: =(B9-B10)*$K$7^(A9+0.5) -> 241.84932 | E9: =SUM(C9:$C$107) -> 20273101 | F9: =SUM(D9:$D$107) -> 95591.211 | G9: =B9/B8 -> 0.99966555 | H9: =1-G9 -> 0.0003344483
A10: 8 | B10: 991460.26 | C10: 752926.38 | D10: =(B10-B11)*$K$7^(A10+0.5) -> 233.621 | E10: =SUM(C10:$C$107) -> 19493576 | F10: =SUM(D10:$D$107) -> 95349.362 | G10: =B10/B9 -> 0.99968437 | H10: =1-G10 -> 0.00031563494
A11: 9 | B11: 991147.29 | C11: 727235.46 | D11: =(B11-B12)*$K$7^(A11+0.5) -> 211.96758 | E11: =SUM(C11:$C$107) -> 18740650 | F11: =SUM(D11:$D$107) -> 95115.741 | G11: =B11/B10 -> 0.99968433 | H11: =1-G11 -> 0.00031566727
A12: 10 | B12: 990853.39 | C12: 702434.61 | D12: =(B12-B13)*$K$7^(A12+0.5) -> 217.99715 | E12: =SUM(C12:$C$107) -> 18013415 | F12: =SUM(D12:$D$107) -> 94903.773 | G12: =B12/B11 -> 0.99970347 | H12: =1-G12 -> 0.00029652722
A13: 11 | B13: 990540.55 | C13: 678466.5 | D13: =(B13-B14)*$K$7^(A13+0.5) -> 210.58033 | E13: =SUM(C13:$C$107) -> 17310980 | F13: =SUM(D13:$D$107) -> 94685.776 | G13: =B13/B12 -> 0.99968427 | H13: =1-G13 -> 0.00031572945
A14: 12 | B14: 990227.77 | C14: 655316.2 | D14: =(B14-B15)*$K$7^(A14+0.5) -> 239.31385 | E14: =SUM(C14:$C$107) -> 16632514 | F14: =SUM(D14:$D$107) -> 94475.196 | G14: =B14/B13 -> 0.99968424 | H14: =1-G14 -> 0.00031576179
A15: 13 | B15: 989859.88 | C15: 632920.52 | D15: =(B15-B16)*$K$7^(A15+0.5) -> 275.2784 | E15: =SUM(C15:$C$107) -> 15977197 | F15: =SUM(D15:$D$107) -> 94235.882 | G15: =B15/B14 -> 0.99962848 | H15: =1-G15 -> 0.0003715242
A16: 14 | B16: 989421.88 | C16: 611246.82 | D16: =(B16-B17)*$K$7^(A16+0.5) -> 326.50369 | E16: =SUM(C16:$C$107) -> 15344277 | F16: =SUM(D16:$D$107) -> 93960.604 | G16: =B16/B15 -> 0.99955752 | H16: =1-G16 -> 0.00044247948
A17: 15 | B17: 988884.2 | C17: 590255.7 | D17: =(B17-B18)*$K$7^(A17+0.5) -> 415.64432 | E17: =SUM(C17:$C$107) -> 14733030 | F17: =SUM(D17:$D$107) -> 93634.1 | G17: =B17/B16 -> 0.99945657 | H17: =1-G17 -> 0.00054342755
A18: 16 | B18: 988175.77 | C18: 569886.81 | D18: =(B18-B19)*$K$7^(A18+0.5) -> 508.08215 | E18: =SUM(C18:$C$107) -> 14142774 | F18: =SUM(D18:$D$107) -> 93218.456 | G18: =B18/B17 -> 0.99928361 | H18: =1-G18 -> 0.00071639382
A19: 17 | B19: 987279.48 | C19: 550115.86 | D19: =(B19-B20)*$K$7^(A19+0.5) -> 609.71127 | E19: =SUM(C19:$C$107) -> 13572887 | F19: =SUM(D19:$D$107) -> 92710.374 | G19: =B19/B18 -> 0.99909298 | H19: =1-G19 -> 0.00090701716
... A107: 105 | B107: 1.5903698 | C107: 0.04293005 | D107: =(B107-B108)*$K$7^(A107+0.5) -> 0.042197937 | E107: =SUM(C107:$C$107) -> 0.04293005 | F107: =SUM(D107:$D$107) -> 0.042197937 | G107: =B107/B106 -> 0.11862005 | H107: =1-G107 -> 0.88137995
A108: 106 | B108: 0 | C108: 0 | D108: =(B108-B109)*$K$7^(A108+0.5) -> 0 | E108: =SUM(C$107:$C108) -> 0.04293005 | F108: =SUM(D$107:$D108) -> 0.042197937 | G108: =B108/B107 -> 0 | H108: =1-G108 -> 1
A109: 107 | B109: 0 | C109: 0 | D109: =(B109-B110)*$K$7^(A109+0.5) -> 0 | E109: =SUM(C$107:$C109) -> 0.04293005 | F109: =SUM(D$107:$D109) -> 0.042197937 | G109: =B109/B108 -> #DIV/0! | H109: =1-G109 -> #DIV/0!
A110: 108 | B110: 0 | C110: 0 | D110: =(B110-B111)*$K$7^(A110+0.5) -> 0 | E110: =SUM(C$107:$C110) -> 0.04293005 | F110: =SUM(D$107:$D110) -> 0.042197937 | G110: =B110/B109 -> #DIV/0! | H110: =1-G110 -> #DIV/0!
A111: 109 | B111: 0 | C111: 0 | D111: =(B111-B112)*$K$7^(A111+0.5) -> 0 | E111: =SUM(C$107:$C111) -> 0.04293005 | F111: =SUM(D$107:$D111) -> 0.042197937 | G111: =B111/B110 -> #DIV/0! | H111: =1-G111 -> #DIV/0!
A112: 110 | B112: 0 | C112: 0 | D112: =(B112-B113)*$K$7^(A112+0.5) -> 0 | E112: =SUM(C$107:$C112) -> 0.04293005 | F112: =SUM(D$107:$D112) -> 0.042197937 | G112: =B112/B111 -> #DIV/0! | H112: =1-G112 -> #DIV/0!
